ddd/__init__.py
ddd/adapters/__init__.py
ddd/adapters/adapter.py
ddd/adapters/message_reader.py
ddd/adapters/event/__init__.py
ddd/adapters/event/event_adapter.py
ddd/adapters/event/event_listener.py
ddd/adapters/event/azure/__init__.py
ddd/adapters/event/azure/azure_event_adapter.py
ddd/adapters/event/kafka/__init__.py
ddd/adapters/event/kafka/kafka_event_adapter.py
ddd/adapters/event/memory/__init__.py
ddd/adapters/event/memory/memory_event_adapter.py
ddd/adapters/http/__init__.py
ddd/adapters/http/exceptions.py
ddd/adapters/http/http_adapter.py
ddd/adapters/job/__init__.py
ddd/adapters/job/ap_scheduler_adapter.py
ddd/adapters/job/exceptions.py
ddd/adapters/job/job_adapter.py
ddd/adapters/job/memory_scheduler_adapter.py
ddd/adapters/job/scheduler_adapter.py
ddd/application/__init__.py
ddd/application/action.py
ddd/application/application_service.py
ddd/application/config.py
ddd/application/domain_registry.py
ddd/application/dummy_application_service.py
ddd/domain/__init__.py
ddd/domain/aggregate.py
ddd/domain/building_block.py
ddd/domain/command.py
ddd/domain/entity.py
ddd/domain/entity_id.py
ddd/domain/entity_id_translator.py
ddd/domain/event_publisher.py
ddd/domain/exceptions.py
ddd/domain/service.py
ddd/domain/value_object.py
ddd/domain/azure/__init__.py
ddd/domain/azure/azure_event_publisher.py
ddd/domain/dummy/__init__.py
ddd/domain/dummy/dummy.py
ddd/domain/dummy/dummy_id.py
ddd/domain/dummy/dummy_repository.py
ddd/domain/dummy/dummy_translator.py
ddd/domain/event/__init__.py
ddd/domain/event/domain_event.py
ddd/domain/event/event.py
ddd/domain/event/integration_event.py
ddd/domain/kafka/__init__.py
ddd/domain/kafka/kafka_event_publisher.py
ddd/domain/memory/__init__.py
ddd/domain/memory/memory_event_publisher.py
ddd/infrastructure/__init__.py
ddd/infrastructure/container.py
ddd/infrastructure/email_service.py
ddd/infrastructure/infrastructure_service.py
ddd/infrastructure/job_service.py
ddd/infrastructure/log_service.py
ddd_for_python-0.9.5.dist-info/LICENSE
ddd_for_python-0.9.5.dist-info/METADATA
ddd_for_python-0.9.5.dist-info/WHEEL
ddd_for_python-0.9.5.dist-info/top_level.txt
ddd_for_python-0.9.5.dist-info/RECORD
