Metadata-Version: 2.1
Name: ddd-for-python
Version: 0.9.5
Summary: A domain-driven design (DDD) framework for Python.
Home-page: https://github.com/runemalm/ddd-for-python
Author: David Runemalm, 2021
Author-email: david.runemalm@gmail.com
License: GNU General Public License v3.0
Project-URL: Documentation, https://ddd-for-python.readthedocs.io/en/latest/
Project-URL: Bug Tracker, https://github.com/runemalm/ddd-for-python/issues
Platform: UNKNOWN
Requires-Python: >=3.8.5
Requires-Dist: addict (>=2.3.0)
Requires-Dist: aiokafka (>=0.7.0)
Requires-Dist: APScheduler (>=3.6.3)
Requires-Dist: arrow (>=0.16.0)
Requires-Dist: asyncpg (>=0.21.0)
Requires-Dist: azure-eventhub (>=5.2.0)
Requires-Dist: azure-eventhub-checkpointstoreblob-aio (>=1.1.1)
Requires-Dist: CMRESHandler (>=1.0.0)
Requires-Dist: python-dotenv (>=0.14.0)
Requires-Dist: slacker-log-handler (>=1.7.1)
Requires-Dist: SQLAlchemy (>=1.3.20)
Requires-Dist: uvloop (>=0.14.0)
